<?xml version="1.0" encoding="utf-8" ?>
<dwsync>
<file name="ace-extra.js" server="217.198.116.5" local="130740792497033480" remote="130686369000000000" Dst="2" />
<file name="ace-elements.js" server="217.198.116.5" local="130740792497110310" remote="130686369600000000" Dst="2" />
<file name="ace.js" server="217.198.116.5" local="130740792497139120" remote="130686369600000000" Dst="2" />
<file name="additional-methods.js" server="217.198.116.5" local="130740792499361670" remote="130686369000000000" Dst="2" />
<file name="bootbox.js" server="217.198.116.5" local="130740792499390340" remote="130686369000000000" Dst="2" />
<file name="bootstrap-colorpicker.js" server="217.198.116.5" local="130740792499421800" remote="130686369000000000" Dst="2" />
<file name="bootstrap-tag.js" server="217.198.116.5" local="130740792501643580" remote="130686369000000000" Dst="2" />
<file name="bootstrap-wysiwyg.js" server="217.198.116.5" local="130740792501674290" remote="130686369000000000" Dst="2" />
<file name="bootstrap.js" server="217.198.116.5" local="130740792503441380" remote="130686369000000000" Dst="2" />
<file name="chosen.jquery.js" server="217.198.116.5" local="130740792503519020" remote="130686369000000000" Dst="2" />
<file name="excanvas.js" server="217.198.116.5" local="130740792536629400" remote="130686369000000000" Dst="2" />
<file name="fullcalendar.js" server="217.198.116.5" local="130740792544883940" remote="130686369600000000" Dst="2" />
<file name="jquery-1.10.2.js" server="217.198.116.5" local="130740792546048030" remote="130686369000000000" Dst="2" />
<file name="jquery.autosize.js" server="217.198.116.5" local="130740792547300270" remote="130686369000000000" Dst="2" />
<file name="jquery-2.0.3.js" server="217.198.116.5" local="130740792547479370" remote="130686369000000000" Dst="2" />
<file name="jquery-ui-1.10.3.custom.js" server="217.198.116.5" local="130740792548959820" remote="130686369000000000" Dst="2" />
<file name="jquery.colorbox.js" server="217.198.116.5" local="130740792549165490" remote="130686369000000000" Dst="2" />
<file name="jquery.easy-pie-chart.js" server="217.198.116.5" local="130740792550843290" remote="130686369000000000" Dst="2" />
<file name="jquery.gritter.js" server="217.198.116.5" local="130740792550956170" remote="130686369000000000" Dst="2" />
<file name="jquery.hotkeys.js" server="217.198.116.5" local="130740792552598620" remote="130686369000000000" Dst="2" />
<file name="jquery.dataTables.js" server="217.198.116.5" local="130740792553601700" remote="130686369600000000" Dst="2" />
<file name="jquery.inputlimiter.1.3.1.js" server="217.198.116.5" local="130740792553714490" remote="130686369000000000" Dst="2" />
<file name="jquery.knob.js" server="217.198.116.5" local="130740792554580440" remote="130686369000000000" Dst="2" />
<file name="jquery.maskedinput.js" server="217.198.116.5" local="130740792555273630" remote="130686369000000000" Dst="2" />
<file name="jquery.mobile.custom.js" server="217.198.116.5" local="130740792556797430" remote="130686369000000000" Dst="2" />
<file name="jquery.slimscroll.js" server="217.198.116.5" local="130740792556923890" remote="130686369000000000" Dst="2" />
<file name="jquery.ui.touch-punch.js" server="217.198.116.5" local="130740792558575020" remote="130686369600000000" Dst="2" />
<file name="jquery.sparkline.js" server="217.198.116.5" local="130740792558837110" remote="130686369000000000" Dst="2" />
<file name="jquery.validate.js" server="217.198.116.5" local="130740792560463220" remote="130686369600000000" Dst="2" />
<file name="respond.src.js" server="217.198.116.5" local="130740792562517430" remote="130686369000000000" Dst="2" />
<file name="spin.js" server="217.198.116.5" local="130740792564862090" remote="130686369000000000" Dst="2" />
<file name="select2.js" server="217.198.116.5" local="130740792566525940" remote="130686369000000000" Dst="2" />
</dwsync>